sabrute/sabrute.py
sabrute/resources/base
sabrute/resources/phantomjs
sabrute/resources/phantomjs.exe
sabrute/resources/phantomjs32
sabrute/resources/phantomjsARM
sabrute-0.1.5.dist-info/LICENSE
sabrute-0.1.5.dist-info/METADATA
sabrute-0.1.5.dist-info/WHEEL
sabrute-0.1.5.dist-info/entry_points.txt
sabrute-0.1.5.dist-info/top_level.txt
sabrute-0.1.5.dist-info/RECORD
