Metadata-Version: 2.1
Name: sabrute
Version: 0.1.5
Summary: Программа для подбора паролей SAMP Mobile
Home-page: https://github.com/rmdlv/sabrute
Author-email: ksdgdfjhgaskfgdjsgf@mail.ru
License: Mozilla Public License 2.0
Project-URL: GitHub, https://github.com/rmdlv/sabrute
Project-URL: Documentation, https://github.com/rmdlv/sabrute/blob/master/README.md
Keywords: samp mobile bruteforce
Platform: UNKNOWN
Requires-Python: >=3.6
Requires-Dist: aiohttp
Requires-Dist: selenium
Requires-Dist: colorama
